{
  "v": 4,
  "entries": {
    "ui-accordionitem--docs": {
      "id": "ui-accordionitem--docs",
      "title": "ui/AccordionItem",
      "name": "Docs",
      "importPath": "./src/components/ui/AccordionItem/AccordionItem.stories.tsx",
      "type": "docs",
      "tags": ["autodocs", "docs"],
      "storiesImports": []
    },
    "ui-accordionitem--closed": {
      "type": "story",
      "id": "ui-accordionitem--closed",
      "name": "Closed",
      "title": "ui/AccordionItem",
      "importPath": "./src/components/ui/AccordionItem/AccordionItem.stories.tsx",
      "tags": ["autodocs", "story"]
    },
    "ui-accordionitem--opened": {
      "type": "story",
      "id": "ui-accordionitem--opened",
      "name": "Opened",
      "title": "ui/AccordionItem",
      "importPath": "./src/components/ui/AccordionItem/AccordionItem.stories.tsx",
      "tags": ["autodocs", "story"]
    },
    "ui-button--docs": {
      "id": "ui-button--docs",
      "title": "ui/Button",
      "name": "Docs",
      "importPath": "./src/components/ui/Button/Button.stories.tsx",
      "type": "docs",
      "tags": ["autodocs", "docs"],
      "storiesImports": []
    },
    "ui-button--forward": {
      "type": "story",
      "id": "ui-button--forward",
      "name": "Forward",
      "title": "ui/Button",
      "importPath": "./src/components/ui/Button/Button.stories.tsx",
      "tags": ["autodocs", "story"]
    },
    "ui-button--back": {
      "type": "story",
      "id": "ui-button--back",
      "name": "Back",
      "title": "ui/Button",
      "importPath": "./src/components/ui/Button/Button.stories.tsx",
      "tags": ["autodocs", "story"]
    },
    "ui-button--login": {
      "type": "story",
      "id": "ui-button--login",
      "name": "Login",
      "title": "ui/Button",
      "importPath": "./src/components/ui/Button/Button.stories.tsx",
      "tags": ["autodocs", "story"]
    },
    "ui-button--without-icon": {
      "type": "story",
      "id": "ui-button--without-icon",
      "name": "Without Icon",
      "title": "ui/Button",
      "importPath": "./src/components/ui/Button/Button.stories.tsx",
      "tags": ["autodocs", "story"]
    },
    "ui-button--select": {
      "type": "story",
      "id": "ui-button--select",
      "name": "Select",
      "title": "ui/Button",
      "importPath": "./src/components/ui/Button/Button.stories.tsx",
      "tags": ["autodocs", "story"]
    },
    "ui-button--cancel": {
      "type": "story",
      "id": "ui-button--cancel",
      "name": "Cancel",
      "title": "ui/Button",
      "importPath": "./src/components/ui/Button/Button.stories.tsx",
      "tags": ["autodocs", "story"]
    },
    "pages-notfoundpage--docs": {
      "id": "pages-notfoundpage--docs",
      "title": "pages/NotFoundPage",
      "name": "Docs",
      "importPath": "./src/pages/NotFoundPage/ui/NotFoundPage.stories.tsx",
      "type": "docs",
      "tags": ["autodocs", "docs"],
      "storiesImports": []
    },
    "pages-notfoundpage--page": {
      "type": "story",
      "id": "pages-notfoundpage--page",
      "name": "Page",
      "title": "pages/NotFoundPage",
      "importPath": "./src/pages/NotFoundPage/ui/NotFoundPage.stories.tsx",
      "tags": ["autodocs", "story"]
    }
  }
}
